the_odds/__init__.py
the_odds/api/__init__.py
the_odds/api/v4.py
the_odds/http_client.py
the_odds/odds_client.py
the_odds/odds_config.py
the_odds/request_helpers.py
the_odds-1.0.2.dist-info/LICENSE
the_odds-1.0.2.dist-info/METADATA
the_odds-1.0.2.dist-info/WHEEL
the_odds-1.0.2.dist-info/RECORD
