Metadata-Version: 2.1
Name: the-odds
Version: 1.0.2
Summary: The-Odds-APi.com Client (unofficial).
Home-page: https://github.com/coreyjs/data-golf-api
License: MIT
Keywords: sports,odds,betting,NHL,NFL,sports-betting,odds-fetching,sports-analytics,sports-odds,odds-calculator,betting-odds,game-odds,sports-data,odds-api,hockey,football,live-odds,sports-metrics,daily-fantasy,sports-stats
Author: Corey Schaf
Author-email: cschaf@gmail.com
Requires-Python: >=3.9,<4.0
Classifier: Development Status :: 4 - Beta
Classifier: Intended Audience :: Developers
Classifier: License :: OSI Approved :: MIT License
Classifier: Programming Language :: Python
Classifier: Programming Language :: Python :: 3
Classifier: Programming Language :: Python :: 3.9
Classifier: Programming Language :: Python :: 3.10
Classifier: Programming Language :: Python :: 3.11
Classifier: Programming Language :: Python :: 3.12
Classifier: Topic :: Software Development :: Libraries
Classifier: Topic :: Software Development :: Libraries :: Python Modules
Requires-Dist: httpx (>=0.27.0,<0.28.0)
Project-URL: Repository, https://github.com/coreyjs/data-golf-api
